---
layout: default
title: "Local Variable Table"
parent: "Java & JVM Internals"
nav_order: 11
permalink: /java/local-variable-table/
---
# 011 — Local Variable Table

`#java` `#jvm` `#internals` `#memory` `#bytecode` `#deep-dive`

⚡ TL;DR — The indexed slot array inside every stack frame that stores a method's parameters and local variables — fixed at compile time, zero GC overhead, lives and dies with its frame.

| #011 | Category: JVM Internals | Difficulty: ★★★ |
|:---|:---|:---|
| **Depends on:** | Stack Frame, Bytecode, Operand Stack | |
| **Used by:** | Every method execution, Debugger, JIT Compiler | |

---

### 📘 Textbook Definition

The Local Variable Table (LVT) is a **fixed-size, indexed array of variable slots within a stack frame** that stores a method's parameters and locally declared variables. Slot 0 holds `this` for instance methods. Each slot holds a primitive value or object reference. `long` and `double` occupy two consecutive slots. The table's size is determined at compile time by `javac` and stored in the `.class` file's `Code` attribute.

---

### 🟢 Simple Definition (Easy)

The Local Variable Table is the method's **named storage cabinet** — every parameter and local variable gets a numbered drawer, and bytecode reads and writes to those drawers by number.

---

### 🔵 Simple Definition (Elaborated)

When `javac` compiles a method, it assigns every parameter and local variable a slot number — like locker numbers. The JVM uses these numbers, not names, at runtime. `iload_2` means "push the integer from slot 2 onto the operand stack" — it doesn't know or care that slot 2 is called `total`. Names are debug metadata, not runtime reality. The table is pre-sized exactly right at compile time — no dynamic resizing, no GC, instant allocation when the frame is pushed.

---

### 🔩 First Principles Explanation

**The problem:**

A method needs to store:

- Its incoming parameters
- Variables it declares during execution
- The `this` reference (for instance methods)

These need to be:

- Instantly accessible by bytecode instructions
- Completely isolated from other methods' variables
- Automatically cleaned up when the method exits

**The naive solution — heap allocation:**

```
Store local vars as objects on heap → GC cleans up
Problem:
  • GC overhead for every method call
  • Slow allocation
  • Cache-unfriendly (heap pointers everywhere)
```

**The right solution — pre-allocated indexed array:**

```
javac analyses the method at compile time:
  • Counts all parameters
  • Counts all local variables
  • Determines maximum slots needed
  • Writes that number into .class file

JVM at runtime:
  • Reads slot count from .class
  • Allocates exactly that many slots on stack
  • No counting, no resizing, no GC
  • Just: frame_base_ptr + (slot_index * slot_size)
```

> Access to any slot = single pointer arithmetic operation. O(1), cache-hot, zero overhead.

---

### ❓ Why Does This Exist — Why Before What

**Without the Local Variable Table:**

**Option A — Use Operand Stack for everything:**

```
Every intermediate AND named variable goes on operand stack
Problem:
  • Stack is LIFO — can't randomly access variable 'a'
    while 'b', 'c', 'd' are on top of it
  • Reading 'a' mid-computation = impossible without
    destroying the stack
  • Code generation becomes nightmarish
```

**Option B — Use heap for local variables:**

```
Allocate local vars as heap objects
Problem:
  • GC pressure on every method call
  • Cache misses — heap is not as cache-hot as stack
  • Pointer chasing for every variable access
  • OOP overhead for primitive integers
```

**Option C — Use CPU registers directly:**

```
Map local vars to actual CPU registers
Problem:
  • CPU-specific — x86 has 16 general registers,
    ARM has different count/rules
  • Methods with 20 local vars → register spilling
  • Bytecode becomes platform-specific
  • Destroys "write once, run anywhere"
```

**What breaks without LVT:**

```
1. Random access to named variables → impossible on pure stack
2. Platform independence → broken if using CPU registers
3. Performance → destroyed if using heap
4. GC pressure → explodes with heap-allocated locals
5. Debugger support → can't inspect named variables
```

**With LVT:**

```
→ Platform-independent indexed access (JIT maps to registers later)
→ O(1) random access to any variable by slot number
→ Zero GC overhead — lives on stack
→ Exact size pre-calculated — no waste, no resize
→ Debugger reads names from .class metadata → human-readable
```

---

### 🧠 Mental Model / Analogy

> Think of a method call as renting a **safety deposit box room** at a bank.
> 
> When you enter (method called), the bank assigns you a room with exactly N numbered boxes (slots) — pre-determined by the vault architect (javac) who designed this room type.
> 
> - Box 0: always holds your ID (this reference)
> - Box 1, 2...: your parameters, handed to you at the door
> - Remaining boxes: empty, ready for things you'll store during your visit
> 
> You can open any box instantly by number — O(1). When you leave (method returns), the entire room is released instantly — no cleanup crew needed.
> 
> The box **numbers** are what matter at runtime. The **names** on the labels (variable names) are just for your convenience — the bank doesn't care.

---

### ⚙️ How It Works — Slot Assignment Rules

---

### 🔄 How It Connects

```
javac compiles method
      ↓
Calculates max slots needed
Writes into .class Code attribute: locals=N
      ↓
Class Loader loads .class
      ↓
Method called → Stack Frame created
      ↓
[Local Variable Table] allocated: N slots
  ← parameters copied in from caller's Operand Stack
      ↓
Bytecode executes:
  iload_N  → LVT slot N → Operand Stack
  istore_N ← Operand Stack → LVT slot N
      ↓
Method returns → Frame popped
  → LVT instantly gone (no GC)
  → Return value was on Operand Stack, passed to caller
```

---

### 💻 Code Example — Slot Assignment in Detail

**Instance method — full slot trace:**

java

```java
public class Order {

    public double calculateTotal(int quantity, double price) {
        double subtotal = quantity * price;
        double tax = subtotal * 0.1;
        return subtotal + tax;
    }
}
```

bash

```bash
javap -c -verbose Order
```

```
public double calculateTotal(int, double);
  descriptor: (ID)D
  flags: ACC_PUBLIC
  Code:
    stack=4       ← max operand stack depth
    locals=6      ← total LVT slots needed
    args_size=3   ← this + quantity + price (double=2)
```

**LVT slot assignment:**

```
Slot 0 → this          (reference, 1 slot)
Slot 1 → quantity      (int,       1 slot)
Slot 2 → price         (double,    2 slots → occupies 2,3)
Slot 4 → subtotal      (double,    2 slots → occupies 4,5)
         ↑ slot 3 is second half of 'price'
         tax would be slot 6,7 BUT javac reuses slots...

Actually with optimisation:
Slot 4,5 → subtotal
Slot 6,7 → tax
locals = 8
```

**Bytecode trace:**

```
 0: iload_1           // push quantity (slot 1) → OS: [qty]
 1: i2d               // convert int→double     → OS: [qty_d]
 2: dload_2           // push price (slots 2,3) → OS: [qty_d, price]
 3: dmul              // pop two doubles, multiply → OS: [subtotal]
 4: dstore 4          // pop → store in slots 4,5 (subtotal)
 6: dload 4           // push subtotal          → OS: [subtotal]
 8: ldc2_w 0.1        // push constant 0.1      → OS: [subtotal, 0.1]
11: dmul              // multiply               → OS: [tax]
12: dstore 6          // store tax in slots 6,7
14: dload 4           // push subtotal          → OS: [subtotal]
16: dload 6           // push tax               → OS: [subtotal, tax]
18: dadd              // add                    → OS: [total]
19: dreturn           // return double to caller
```

---

**Slot reuse — javac optimisation:**

java

```java
public static void slotReuse(boolean flag) {
    if (flag) {
        int x = 10;         // x gets slot 1
        System.out.println(x);
    }   // x goes out of scope here — slot 1 now FREE

    if (!flag) {
        int y = 20;         // y REUSES slot 1 (x is gone)
        System.out.println(y);
    }
    // max locals = 2 (slot 0: flag, slot 1: x OR y)
    // NOT 3 — javac is smarter than that
}
```

bash

```bash
javap -verbose SlotReuse | grep locals
# locals=2   ← confirmed: slot reuse happened
# NOT locals=3
```

---

**Debugger metadata — variable names are NOT in bytecode:**

bash

```bash
# Without debug info (default javac):
javac SlotReuse.java
javap -l SlotReuse
# LocalVariableTable: NOT SHOWN
# Debugger sees: slot 0, slot 1 — no names

# With debug info:
javac -g SlotReuse.java
javap -l SlotReuse
```

```
LocalVariableTable:
  Start  Length  Slot  Name        Signature
      0      20     0  flag        Z          ← boolean
      3       8     1  x           I          ← int
     12       8     1  y           I          ← int, SAME slot 1!
```

> The debugger uses this metadata to show you `x` and `y` as names — but the JVM only ever sees slot 1. Names are purely for human consumption, compiled in only with `-g` flag or by default in most build tools.

---

**The `this` reference — just slot 0:**

java

```java
public class Counter {
    private int count = 0;

    public void increment() {
        // 'this' is slot 0 — invisible in source, present in bytecode
        this.count++;
    }
}
```

```
Bytecode for increment():
  0: aload_0          // push 'this' (slot 0) → OS: [this_ref]
  1: aload_0          // push 'this' again    → OS: [this_ref, this_ref]
  2: getfield count   // pop ref, get field   → OS: [this_ref, count_val]
  5: iconst_1         // push 1               → OS: [this_ref, count_val, 1]
  6: iadd             // add                  → OS: [this_ref, count_val+1]
  7: putfield count   // pop ref+val, store field → OS: []
 10: return
```

> Every `this.field` access = `aload_0` + `getfield`. `this` is not magic — it's slot 0, an ordinary reference.

---

**long/double two-slot behaviour:**

java

```java
public static void twoSlots(int a, long b, double c, int d) {
    // Slot assignment:
    // slot 0 → a     (int,    1 slot)
    // slot 1 → b     (long,   2 slots → 1,2)
    // slot 3 → c     (double, 2 slots → 3,4)
    // slot 5 → d     (int,    1 slot)
    // total: 6 slots for 4 parameters
}
```

bash

```bash
javap -verbose TwoSlots | grep locals
# locals=6
# args_size=6  ← JVM counts slot consumption, not param count
```

---

### ⚙️ LVT Size Calculation — How javac Does It

```
javac performs LIVENESS ANALYSIS:

1. Build control flow graph of method
2. Track which variables are "live" at each point
3. Assign slots — dead variable's slot can be reused
4. Calculate maximum simultaneous live slots = locals=N

Example:
  void method() {
      int a = 1;     // slot 1 live
      int b = 2;     // slot 2 live  → max so far: 3 (this+a+b)
      use(a, b);
      // a, b dead here
      int c = 3;     // slot 1 reused (a was here)
      int d = 4;     // slot 2 reused (b was here)
      use(c, d);
  }
  locals = 3   (not 5)
  ← javac reused slots 1,2
```

---

### ⚠️ Common Misconceptions

|Misconception|Reality|
|---|---|
|"Variable names exist at runtime"|Names are **debug metadata** — JVM only uses slot numbers|
|"`this` is special/magic"|`this` is **slot 0** — an ordinary reference in LVT|
|"Each variable always gets its own slot"|javac **reuses slots** when variables go out of scope|
|"long/double = 1 slot"|They consume **2 consecutive slots** — category 2 types|
|"LVT can grow during execution"|Size is **fixed at compile time** — zero dynamic resizing|
|"boolean/byte/char have their own slot type"|All stored as **int** in LVT — JVM has no sub-int slot types|
|"Static and instance methods work the same"|Static methods have **no slot 0** — no `this` reference|

---

### 🔥 Pitfalls in Production

**1. Missing debug info — blind debugging**

bash

```bash
# Production builds often strip debug info for size:
javac -g:none MyClass.java  # no debug info at all
# or Maven with:
<compilerArg>-g:none</compilerArg>

# Result: debugger shows slot numbers, not names
# Stack traces show line numbers as -1 or "Unknown Source"
# Profilers can't show variable names

# Recommendation: always compile with -g (default in Maven/Gradle)
# Size overhead is minimal (~5-10%) vs massive debug value
# Especially critical for production heap dumps
```

**2. Slot reuse surprises in bytecode manipulation**

java

```java
// You generate bytecode with ASM expecting:
// slot 1 = variable 'x' throughout method
// But javac (or your own generator) reused slot 1 for 'y'
// after 'x' went out of scope

// Symptom: wrong variable value read from slot
// Diagnosis: javap -l MyClass  → check LocalVariableTable
// shows slot start/length ranges

// Fix: in ASM, use LocalVariableNode to track slot lifetimes
//      or use COMPUTE_FRAMES flag to let ASM handle it
```

**3. Large LVT in hot methods — JIT pressure**

java

```java
// Method with many local variables:
public void process(Order order) {
    int id          = order.getId();
    String name     = order.getName();
    double price    = order.getPrice();
    int quantity    = order.getQuantity();
    double subtotal = price * quantity;
    double discount = calculateDiscount(subtotal);
    double tax      = calculateTax(subtotal - discount);
    double total    = subtotal - discount + tax;
    String status   = determineStatus(total);
    // ... 20 more variables
}
// Large LVT → more slots to map to CPU registers
// JIT register allocator has to spill excess to stack
// → More memory traffic → slower JIT output

// Fix: extract sub-methods → smaller frames → better JIT
```

**4. Thread-safety illusion with reference slots**

java

```java
public void process() {
    // 'list' reference is in LVT → thread-local → safe ✅
    List<Order> list = new ArrayList<>();

    // BUT: if list was passed in as parameter:
    // the REFERENCE is in LVT → thread-local
    // the OBJECT it points to is on HEAP → shared ❌
    list.add(new Order());  // safe if list created here

    // Passed-in list:
    public void process(List<Order> list) {
        list.add(new Order()); // ← NOT thread-safe
        // list reference in slot 1 is thread-local
        // but the ArrayList object is shared on heap
    }
}
```

---

### 🔗 Related Keywords

- `Stack Frame` — the container holding the LVT
- `Operand Stack` — the working counterpart to LVT
- `Bytecode` — uses slot indices (`iload_N`, `istore_N`) to access LVT
- `javac` — performs liveness analysis and assigns slots
- `javap -l` — reveals LVT slot assignments and name metadata
- `this` — always slot 0 in instance method LVT
- `long / double` — category 2 types; consume 2 LVT slots
- `Escape Analysis` — JVM may eliminate LVT entries entirely
- `JIT Compiler` — maps LVT slots to CPU registers
- `Debugger (JDWP)` — reads LVT metadata to show variable names
- `ASM / ByteBuddy` — must correctly declare LVT when generating bytecode

---

### 📌 Quick Reference Card

---

**Entry 011 complete.**

### 🧠 Think About This Before We Continue

**Q1.** `javac` reuses LVT slots when variables go out of scope. Now consider this scenario: you're writing a security-sensitive method that stores a password in a local `char[]` variable, zeroes it out, then the variable goes out of scope. The slot gets reused by another variable. What are the implications — and does zeroing actually guarantee the sensitive data is gone?

**Q2.** The JIT compiler's register allocator maps LVT slots to CPU registers. A method has 20 local variables but x86-64 only has 16 general-purpose registers. What has to happen — and what performance implications does that have for methods with many local variables?

---

Next up: **012 — Object Header** — the hidden metadata prepended to every object on the heap: Mark Word, Klass Pointer, array length, how they enable locking, GC, and type checking — and why every object costs more memory than its fields suggest.
