---
layout: default
title: "Operand Stack"
parent: "Java Fundamentals"
nav_order: 10
permalink: /java/operand-stack/
---
ðŸ·ï¸ Tags â€” #java #jvm #internals #bytecode #deep-dive

âš¡ TL;DR â€” The per-frame LIFO working memory where bytecode instructions push operands, perform operations, and pass results â€” the JVM's calculation scratch pad. 

```
â”Œâ”€â”€â”€â”€â”€â”€â”€â”€â”€â”€â”€â”€â”€â”€â”€â”€â”€â”€â”€â”€â”€â”€â”€â”€â”€â”€â”€â”€â”€â”€â”€â”€â”€â”€â”€â”€â”€â”€â”€â”€â”€â”€â”€â”€â”€â”€â”€â”€â”€â”€â”€â”€â”€â”€â”
â”‚ #010  â”‚ Category: JVM Internals  â”‚ Difficulty: â˜…â˜…â˜…   â”‚
â”‚ Depends on: Stack Frame,         â”‚ Used by: Every    â”‚
â”‚ Bytecode, Local Variable Table   â”‚ bytecode instr,   â”‚
â”‚                                  â”‚ JIT Compiler      â”‚
â””â”€â”€â”€â”€â”€â”€â”€â”€â”€â”€â”€â”€â”€â”€â”€â”€â”€â”€â”€â”€â”€â”€â”€â”€â”€â”€â”€â”€â”€â”€â”€â”€â”€â”€â”€â”€â”€â”€â”€â”€â”€â”€â”€â”€â”€â”€â”€â”€â”€â”€â”€â”€â”€â”€â”˜
```

---

#### ðŸ“˜ Textbook Definition

The Operand Stack is a **LIFO stack structure within each stack frame** that serves as the working memory for bytecode instruction execution. Instructions load values onto it from the Local Variable Table or constants, perform operations that consume and produce values on it, and pass return values or method arguments through it. Its maximum depth is determined at compile time and stored in the class file.

---

#### ðŸŸ¢ Simple Definition (Easy)

The Operand Stack is the JVM's **calculator display** â€” values get pushed on, operations consume them and push results back, all within a single method's execution.

---

#### ðŸ”µ Simple Definition (Elaborated)

Every bytecode instruction either pushes values onto the Operand Stack, pops values off it, or both. It's the only place arithmetic, comparisons, and method argument passing actually happen. Unlike the Local Variable Table which has named slots, the Operand Stack is positional â€” you push, operate, pop. It's completely separate from other frames' operand stacks, making every method's calculations fully isolated.

---

#### ðŸ”© First Principles Explanation

**The problem:**

The JVM needs to execute arbitrary computations â€” arithmetic, comparisons, method calls â€” across any CPU architecture. Real CPUs use **registers** for this (x86 has EAX, EBX, ECX etc). But:

```
x86 registers:  EAX, EBX, ECX, EDX  (4 general purpose)
ARM registers:  R0-R12               (13 general purpose)
RISC-V:         x0-x31              (32 registers)
```

If bytecode used registers, it would be **CPU-specific** â€” destroying platform independence. Different CPUs have different numbers of registers with different rules.

**The insight:**

> "Use a stack instead of registers. Stack operations need zero operand addresses â€” just push and pop. Works identically on any CPU."

```
Register-based (CPU specific):
  ADD EAX, EBX     â† names specific registers

Stack-based (CPU independent):
  iload_0          â† push whatever is in slot 0
  iload_1          â† push whatever is in slot 1
  iadd             â† pop two, add, push result
  (no register names â€” works on any CPU)
```

The JIT compiler then maps these stack operations to the actual CPU registers of the target machine â€” that translation is the JIT's job, not bytecode's.

---

#### â“ Why Does This Exist â€” Why Before What

**Without the Operand Stack:**

The JVM would need CPU-specific bytecode â€” different `.class` files for x86, ARM, RISC-V. Java's core promise â€” "write once, run anywhere" â€” collapses immediately.

OR the JVM would need to use only the Local Variable Table for everything â€” named temporary variables for every intermediate calculation step:

java

```java
// Without operand stack â€” every intermediate needs a named slot:
int temp1 = a;
int temp2 = b;
int temp3 = temp1 + temp2;
int temp4 = c;
int result = temp3 * temp4;

// With operand stack â€” intermediates are anonymous, no slots needed:
push a, push b, add, push c, multiply â†’ result
```

Every temporary calculation result would consume a Local Variable Table slot â€” exploding frame size for complex expressions.

**What breaks without it:**

```
1. Platform independence â€” gone (need CPU-specific bytecode)
2. Frame size efficiency â€” explodes (every temp needs a named slot)
3. Method argument passing â€” no clean mechanism
4. Return value delivery â€” no standard way to hand value to caller
5. Expression evaluation â€” no way to compose operations
```

**With the Operand Stack:**

Single unified mechanism handles ALL of: arithmetic, comparisons, method argument preparation, return value delivery â€” platform-independently and efficiently.

---

#### ðŸ§  Mental Model / Analogy

> Think of the Operand Stack as an **RPN calculator** (Reverse Polish Notation â€” like old HP calculators).
> 
> Normal calculator: `3 + 4 =` RPN calculator: `3 ENTER 4 ENTER +`
> 
> You push numbers, then apply the operation. The result sits on top ready for the next operation. No parentheses needed. No named registers. Just push, operate, result.
> 
> `(3 + 4) * 2`:
> 
> ```
> Push 3  â†’ [3]
> Push 4  â†’ [3, 4]
> Add     â†’ [7]
> Push 2  â†’ [7, 2]
> Multiplyâ†’ [14]
> ```
> 
> The JVM is literally an RPN calculator executing bytecode.

---

#### âš™ï¸ How It Works â€” Instruction Categories

Every bytecode instruction has a **precise contract** with the operand stack â€” defined number of values consumed (popped) and produced (pushed):

```
â”Œâ”€â”€â”€â”€â”€â”€â”€â”€â”€â”€â”€â”€â”€â”€â”€â”€â”€â”€â”€â”€â”€â”€â”€â”€â”€â”€â”€â”€â”€â”€â”€â”€â”€â”€â”€â”€â”€â”€â”€â”€â”€â”€â”€â”€â”€â”€â”€â”€â”€â”€â”€â”€â”€â”€â”€â”€â”€â”
â”‚           BYTECODE â†’ OPERAND STACK CONTRACT             â”‚
â”‚                                                         â”‚
â”‚  LOAD instructions (LVT â†’ OS):                         â”‚
â”‚  iload_N    pops: 0  pushes: 1 (int from slot N)        â”‚
â”‚  aload_N    pops: 0  pushes: 1 (ref from slot N)        â”‚
â”‚  lload_N    pops: 0  pushes: 2 (long = 2 stack slots)   â”‚
â”‚  iconst_N   pops: 0  pushes: 1 (constant int)           â”‚
â”‚                                                         â”‚
â”‚  STORE instructions (OS â†’ LVT):                        â”‚
â”‚  istore_N   pops: 1  pushes: 0 (store int to slot N)    â”‚
â”‚  astore_N   pops: 1  pushes: 0 (store ref to slot N)    â”‚
â”‚                                                         â”‚
â”‚  ARITHMETIC instructions:                              â”‚
â”‚  iadd        pops: 2  pushes: 1  (int + int)            â”‚
â”‚  isub        pops: 2  pushes: 1  (int - int)            â”‚
â”‚  imul        pops: 2  pushes: 1  (int * int)            â”‚
â”‚  idiv        pops: 2  pushes: 1  (int / int)            â”‚
â”‚  ineg        pops: 1  pushes: 1  (negate int)           â”‚
â”‚                                                         â”‚
â”‚  COMPARISON instructions:                              â”‚
â”‚  if_icmpeq   pops: 2  pushes: 0  (branch if equal)      â”‚
â”‚  if_icmplt   pops: 2  pushes: 0  (branch if less than)  â”‚
â”‚                                                         â”‚
â”‚  STACK manipulation:                                   â”‚
â”‚  dup         pops: 0  pushes: 1  (duplicate top)        â”‚
â”‚  pop         pops: 1  pushes: 0  (discard top)          â”‚
â”‚  swap        pops: 2  pushes: 2  (swap top two)         â”‚
â”‚                                                         â”‚
â”‚  METHOD invocation:                                    â”‚
â”‚  invokevirtual  pops: N+1  pushes: 0 or 1              â”‚
â”‚    (pops objectref + N args, pushes return value)       â”‚
â”‚                                                         â”‚
â”‚  RETURN:                                               â”‚
â”‚  ireturn     pops: 1  pushes: 0  (returns int to caller)â”‚
â”‚  return      pops: 0  pushes: 0  (void return)          â”‚
â””â”€â”€â”€â”€â”€â”€â”€â”€â”€â”€â”€â”€â”€â”€â”€â”€â”€â”€â”€â”€â”€â”€â”€â”€â”€â”€â”€â”€â”€â”€â”€â”€â”€â”€â”€â”€â”€â”€â”€â”€â”€â”€â”€â”€â”€â”€â”€â”€â”€â”€â”€â”€â”€â”€â”€â”€â”€â”˜
```

---

#### ðŸ”„ How It Connects

```
Local Variable Table          Operand Stack
â”€â”€â”€â”€â”€â”€â”€â”€â”€â”€â”€â”€â”€â”€â”€â”€â”€â”€â”€â”€          â”€â”€â”€â”€â”€â”€â”€â”€â”€â”€â”€â”€â”€
[slot 0: this    ]   iload â†’  [ value      ]
[slot 1: a=3     ]   iload â†’  [ value      ]  â†’ iadd â†’ [ result ]
[slot 2: b=4     ]            [ value      ]
[slot 3: result  ]  â† istore  [ result     ]

                              Method args assembled here
                              before invokevirtual

                              Return value lands here
                              from called method
```

---

#### ðŸ’» Code Example â€” Deep Execution Traces

**Example 1 â€” Compound arithmetic expression:**

java

```java
public static int compute(int a, int b, int c) {
    return (a + b) * c;
}
```

bash

```bash
javap -c Example
```

```
public static int compute(int, int, int);
  Code:
     0: iload_0       // push a
     1: iload_1       // push b
     2: iadd          // pop a,b â†’ push (a+b)
     3: iload_2       // push c
     4: imul          // pop (a+b),c â†’ push (a+b)*c
     5: ireturn       // pop result â†’ return to caller
```

**Step-by-step operand stack trace â€” `compute(3, 4, 5)`:**

```
PC  Instruction   Operand Stack      Local Var Table
â”€â”€  â”€â”€â”€â”€â”€â”€â”€â”€â”€â”€â”€   â”€â”€â”€â”€â”€â”€â”€â”€â”€â”€â”€â”€â”€      â”€â”€â”€â”€â”€â”€â”€â”€â”€â”€â”€â”€â”€â”€â”€
    (start)       []                 [a=3, b=4, c=5]
0   iload_0       [3]                [a=3, b=4, c=5]
1   iload_1       [3, 4]             [a=3, b=4, c=5]
2   iadd          [7]                [a=3, b=4, c=5]
3   iload_2       [7, 5]             [a=3, b=4, c=5]
4   imul          [35]               [a=3, b=4, c=5]
5   ireturn       []                 (returns 35)
```

---

**Example 2 â€” String concatenation (reveals `dup` instruction):**

java

```java
public static void greet(String name) {
    String msg = "Hello " + name;
}
```

```
// Simplified bytecode (Java 9+ uses invokedynamic for concat):
// Java 8 style for illustration:
  new StringBuilder          // push ref to new SB
  dup                        // duplicate ref on stack
                             // â† why? invokevirtual needs ref
                             //   AND we need ref to stay on stack
  invokespecial SB.<init>    // pop one ref â†’ initialize SB
                             // other ref still on stack
  ldc "Hello "               // push "Hello " constant
  invokevirtual SB.append    // pop ref + "Hello " â†’ push SB ref
  aload_0                    // push name
  invokevirtual SB.append    // pop ref + name â†’ push SB ref
  invokevirtual SB.toString  // pop ref â†’ push String result
  astore_1                   // pop â†’ store in slot 1 (msg)
```

**Why `dup` exists â€” the construction pattern:**

```
After new StringBuilder:
  OS: [ref]

After dup:
  OS: [ref, ref]   â† two copies

invokespecial <init> consumes one ref:
  OS: [ref]        â† one copy survives

Now we can chain .append() calls using the surviving ref
```

> `dup` exists precisely because `new` pushes a ref but `<init>` consumes it â€” without `dup` you'd lose the reference to the newly constructed object.

---

**Example 3 â€” Method argument passing:**

java

```java
public static void main(String[] args) {
    int result = Math.max(10, 20);
}
```

```
MAIN FRAME operand stack:
  iconst 10      â†’ [10]
  iconst 20      â†’ [10, 20]
  invokestatic Math.max
    â†“
    args 10, 20 POPPED from main's operand stack
    PASSED to max()'s Local Variable Table slots 0,1

MAX FRAME:
  LVT: [a=10, b=20]
  ... executes ...
  ireturn 20
    â†“
    20 PUSHED onto main's operand stack

MAIN FRAME operand stack:
  [20]  â† return value landed here
  istore_1  â†’ stored in result
```

---

**Example 4 â€” long/double take TWO stack slots:**

java

```java
public static long add(long a, long b) {
    return a + b;
}
```

```
  lload_0    // push long a â†’ occupies 2 stack slots
             // OS: [a_high, a_low]  (conceptually)
  lload_2    // push long b â†’ slots 0,1 were a; slots 2,3 are b
             // OS: [a, b]  (each takes 2 slots)
  ladd       // pop two longs â†’ push one long result
  lreturn    // return long
```

> The JVM spec treats `long` and `double` as **category 2** values â€” they consume two consecutive slots in both the Local Variable Table AND the Operand Stack. This is why `lload_0` loads from slot 0 but next parameter is at slot 2, not slot 1.

---

**Example 5 â€” Verifying stack depth at compile time:**

bash

```bash
javap -verbose Example | grep stack
# stack=2   â† max operand stack depth this method needs
# If any execution path requires depth 3 â†’ compile error
# JVM verifier checks this at load time too
```

---

#### âš ï¸ Common Misconceptions

|Misconception|Reality|
|---|---|
|"Operand Stack = Local Variable Table"|Completely separate structures with different roles|
|"Operand Stack persists between method calls"|Each frame has its **own** fresh operand stack|
|"Values sit in operand stack long-term"|OS is **transient** â€” values pushed, operated on, popped quickly|
|"Stack depth is unlimited"|Fixed at **compile time** â€” JVM verifier enforces it|
|"long/double = 1 stack slot"|They take **2 slots** â€” category 2 computational types|
|"JIT uses the operand stack"|JIT **eliminates** the operand stack â€” maps directly to CPU registers|

---

#### ðŸ”¥ Pitfalls in Production

**1. Bytecode manipulation libraries getting stack depths wrong**

java

```java
// When using ASM/ByteBuddy to generate bytecode manually:
// Must declare correct max stack depth or JVM verifier rejects class

// ASM example:
MethodVisitor mv = cw.visitMethod(...);
mv.visitCode();
mv.visitVarInsn(ILOAD, 0);    // push
mv.visitVarInsn(ILOAD, 1);    // push  â†’ depth=2
mv.visitInsn(IADD);           // pop,pop,push â†’ depth=1
mv.visitInsn(IRETURN);        // pop â†’ depth=0

// Must tell ASM max stack depth:
mv.visitMaxs(2, 3);  // maxStack=2, maxLocals=3
// Wrong value â†’ VerifyError at class load time

// Better: let ASM compute it
mv.visitMaxs(0, 0);  // zeros = "ASM, compute for me"
cw.visitEnd();       // requires ClassWriter.COMPUTE_MAXS flag
```

**2. Understanding NullPointerException location in bytecode**

java

```java
// Java 14+ helpful NPEs tell you EXACTLY which operand was null:
// "Cannot invoke String.length() because 'str' is null"

// Before Java 14, NPE just said:
// NullPointerException (no message)
// You had to deduce from stack trace line number + bytecode

// Enable helpful NPEs (default Java 14+, opt-in Java 14):
java -XX:+ShowCodeDetailsInExceptionMessages MyApp

// Production value: precise NPE messages = faster diagnosis
// No performance cost â€” only computed when exception thrown
```

**3. JIT inlining makes operand stack invisible to profilers**

```
JIT inlines small methods â†’ their frames disappear
â†’ profiler shows time spent in CALLER, not callee
â†’ looks like your code is slow when it's the inlined method

Example:
  myService.process()    appears to take 200ms in profiler
  But actually:
    getUser()     inlined â†’ invisible
    validate()    inlined â†’ invisible
    transform()   inlined â†’ invisible
  All their operand stack ops merged into process() frame

Fix: use async profilers (async-profiler, JFR)
  that sample at safepoints AND non-safepoints
  â†’ see true call breakdown even after inlining
```

---

#### ðŸ”— Related Keywords

- `Stack Frame` â€” the container that holds the Operand Stack
- `Local Variable Table` â€” the named storage counterpart to OS
- `Bytecode` â€” instructions that define all OS operations
- `JIT Compiler` â€” eliminates OS entirely, maps to CPU registers
- `iload/istore` â€” primary instructions moving values between LVT and OS
- `dup` â€” critical OS manipulation instruction for object construction
- `invokedynamic` â€” method call instruction using OS for arg passing
- `VerifyError` â€” thrown when OS depth constraints violated
- `long/double` â€” category 2 types; occupy 2 OS slots
- `ASM / ByteBuddy` â€” libraries that must correctly declare max OS depth

---

#### ðŸ“Œ Quick Reference Card

```
â”Œâ”€â”€â”€â”€â”€â”€â”€â”€â”€â”€â”€â”€â”€â”€â”€â”€â”€â”€â”€â”€â”€â”€â”€â”€â”€â”€â”€â”€â”€â”€â”€â”€â”€â”€â”€â”€â”€â”€â”€â”€â”€â”€â”€â”€â”€â”€â”€â”€â”€â”€â”€â”€â”€â”€â”€â”€â”€â”€â”
â”‚ KEY IDEA     â”‚ Per-frame LIFO working memory â€” the JVM's â”‚
â”‚              â”‚ calculation engine, CPU-register-         â”‚
â”‚              â”‚ independent by design                     â”‚
â”œâ”€â”€â”€â”€â”€â”€â”€â”€â”€â”€â”€â”€â”€â”€â”€â”€â”€â”€â”€â”€â”€â”€â”€â”€â”€â”€â”€â”€â”€â”€â”€â”€â”€â”€â”€â”€â”€â”€â”€â”€â”€â”€â”€â”€â”€â”€â”€â”€â”€â”€â”€â”€â”€â”€â”€â”€â”€â”€â”¤
â”‚ USE WHEN     â”‚ Always present â€” understanding it unlocks â”‚
â”‚              â”‚ bytecode reading, JIT behaviour,          â”‚
â”‚              â”‚ and bytecode generation tools             â”‚
â”œâ”€â”€â”€â”€â”€â”€â”€â”€â”€â”€â”€â”€â”€â”€â”€â”€â”€â”€â”€â”€â”€â”€â”€â”€â”€â”€â”€â”€â”€â”€â”€â”€â”€â”€â”€â”€â”€â”€â”€â”€â”€â”€â”€â”€â”€â”€â”€â”€â”€â”€â”€â”€â”€â”€â”€â”€â”€â”€â”¤
â”‚ AVOID WHEN   â”‚ Don't manually track operand stack in     â”‚
â”‚              â”‚ bytecode manipulation â€” let ASM/ByteBuddy â”‚
â”‚              â”‚ compute maxStack automatically            â”‚
â”œâ”€â”€â”€â”€â”€â”€â”€â”€â”€â”€â”€â”€â”€â”€â”€â”€â”€â”€â”€â”€â”€â”€â”€â”€â”€â”€â”€â”€â”€â”€â”€â”€â”€â”€â”€â”€â”€â”€â”€â”€â”€â”€â”€â”€â”€â”€â”€â”€â”€â”€â”€â”€â”€â”€â”€â”€â”€â”€â”¤
â”‚ ONE-LINER    â”‚ "Operand Stack = the JVM's RPN calculator â”‚
â”‚              â”‚  â€” push values, apply operations,         â”‚
â”‚              â”‚  collect result"                          â”‚
â”œâ”€â”€â”€â”€â”€â”€â”€â”€â”€â”€â”€â”€â”€â”€â”€â”€â”€â”€â”€â”€â”€â”€â”€â”€â”€â”€â”€â”€â”€â”€â”€â”€â”€â”€â”€â”€â”€â”€â”€â”€â”€â”€â”€â”€â”€â”€â”€â”€â”€â”€â”€â”€â”€â”€â”€â”€â”€â”€â”¤
â”‚ NEXT EXPLORE â”‚ Local Variable Table â†’ JIT Register       â”‚
â”‚              â”‚ Allocation â†’ invokedynamic â†’              â”‚
â”‚              â”‚ ASM Bytecode Generation                   â”‚
â””â”€â”€â”€â”€â”€â”€â”€â”€â”€â”€â”€â”€â”€â”€â”€â”€â”€â”€â”€â”€â”€â”€â”€â”€â”€â”€â”€â”€â”€â”€â”€â”€â”€â”€â”€â”€â”€â”€â”€â”€â”€â”€â”€â”€â”€â”€â”€â”€â”€â”€â”€â”€â”€â”€â”€â”€â”€â”€â”˜
```

---

**Entry 010 complete.**

#### ðŸ§  Think About This Before We Continue

**Q1.** The JIT compiler's job is to map JVM stack-based bytecode onto real CPU register-based instructions. What fundamentally has to happen during that translation â€” and why does the JIT produce **faster** code than the interpreter even though they both start from the same bytecode?

**Q2.** Look at this bytecode sequence and reconstruct the original Java source expression:

```
iload_1
iload_2
imul
iload_3
iload_1
isub
idiv
ireturn
```

Trace the operand stack step by step â€” what does this method compute?

---

Next up: **011 â€” Local Variable Table** â€” the named slot storage inside every frame, how javac assigns slots, the `this` reference, long/double two-slot behaviour, and why slot reuse can surprise debuggers.
