---
layout: default
title: "Bytecode"
parent: "Java & JVM Internals"
nav_order: 264
permalink: /java/bytecode/
---
# 264 — Bytecode

`#java` `#jvm` `#internals` `#deep-dive`

⚡ TL;DR — Platform-neutral instructions javac produces and the JVM executes.

| #264 | category: Java & JVM Internals
|:---|:---|:---|
| **Depends on:** | JVM, javac | |
| **Used by:** | JIT Compiler, Class Loader, JVM | |

---

### 📘 Textbook Definition

Java bytecode is the **intermediate, platform-independent instruction set** produced by the Java compiler (`javac`) from `.java` source files. It is stored in `.class` files and executed by the JVM — either interpreted directly or JIT-compiled into native machine code at runtime.

---

### 🟢 Simple Definition (Easy)

Bytecode is the **compiled form of your Java code** — not human-readable source, not machine-specific binary — it's a middle format that any JVM on any platform can run.

---

### 🔵 Simple Definition (Elaborated)

When you run `javac`, your `.java` source is transformed into bytecode — a set of compact, low-level instructions designed specifically for the JVM's execution engine. These instructions are more abstract than CPU assembly (they don't care about registers or memory addresses) but more concrete than Java source. The JVM reads them and either interprets or compiles them to native code for your specific CPU.

---

### 🔩 First Principles Explanation

**The core problem:**

Native machine code is CPU-specific:

```
x86 assembly:    MOV EAX, 1 / ADD EAX, EBX
ARM assembly:    MOV R0, #1 / ADD R0, R0, R1
```

The same program needs different binaries for every CPU. That's the C/C++ world.

**Java's insight:**

> "Compile once to a neutral instruction set. Let the JVM — which IS platform-specific — handle the final translation."

```
Java Source (.java)
      ↓  javac
Bytecode (.class)        ← ONE format, runs everywhere
      ↓  JVM (per platform)
Native Machine Code      ← CPU-specific, generated at runtime
```

Bytecode is the **universal contract** between Java programs and the JVM.

---

### 🧠 Mental Model / Analogy

> Think of bytecode as **sheet music**.
> 
> The composer (developer) writes it once in a standard notation. Any orchestra (JVM) anywhere in the world can read and perform it — on their own instruments (CPU/OS). The sheet music itself doesn't make sound — it needs a performer to interpret it into actual music (machine code).

The sheet music is platform-independent. The performance is platform-specific.

---

### ⚙️ How It Works — Structure of a `.class` File

A `.class` file is a **precisely structured binary format**. Not random bytes — every position means something.

**Magic Number `0xCAFEBABE`** — James Gosling (Java's creator) chose this. The JVM checks this first — if it's not present, the file is rejected immediately.

---

### ⚙️ The Bytecode Instruction Set

The JVM has ~200 instructions (opcodes). Each is **1 byte** — hence "byte-code."

They operate on a **stack-based virtual machine** — not register-based like real CPUs.

**Key instruction categories:**

|Category|Examples|What They Do|
|---|---|---|
|Load/Store|`iload`, `istore`, `aload`, `astore`|Move between local vars ↔ stack|
|Arithmetic|`iadd`, `isub`, `imul`, `idiv`|Integer math on stack|
|Type conversion|`i2l`, `i2f`, `l2i`|Cast between primitives|
|Object ops|`new`, `getfield`, `putfield`, `invokevirtual`|OOP operations|
|Control flow|`goto`, `ifeq`, `ifne`, `iflt`|Branches, loops|
|Method calls|`invokevirtual`, `invokespecial`, `invokestatic`, `invokeinterface`, `invokedynamic`|Method dispatch|
|Stack ops|`pop`, `dup`, `swap`|Manipulate stack directly|
|Return|`ireturn`, `areturn`, `return`|Return from method|

---

### 💻 Code Example — Source to Bytecode, Step by Step

**Java Source:**

java

```java
public class Calculator {
    public int add(int a, int b) {
        return a + b;
    }

    public int max(int a, int b) {
        if (a > b) return a;
        return b;
    }
}
```

**Compile and disassemble:**

bash

```bash
javac Calculator.java
javap -c Calculator
```

**Bytecode output — `add` method:**

```
public int add(int, int);
  Code:
     0: iload_1      // push local var slot 1 (a) → stack: [a]
     1: iload_2      // push local var slot 2 (b) → stack: [a, b]
     2: iadd         // pop a,b → add → push result  stack: [a+b]
     3: ireturn      // pop and return top of stack
```

**Execution trace — `add(3, 4)`:**

```
Instruction    Operand Stack    Local Vars
─────────────  ───────────────  ──────────────────
(start)        []               [this, a=3, b=4]
iload_1        [3]              [this, a=3, b=4]
iload_2        [3, 4]           [this, a=3, b=4]
iadd           [7]              [this, a=3, b=4]
ireturn        []               (returns 7)
```

**Bytecode output — `max` method (with branch):**

```
public int max(int, int);
  Code:
     0: iload_1      // push a
     1: iload_2      // push b
     2: if_icmple 7  // if a <= b, jump to instruction 7
     5: iload_1      // push a (the return value)
     6: ireturn      // return a
     7: iload_2      // push b
     8: ireturn      // return b
```

> Notice: `if/else` in Java → `if_icmple` (if-int-compare-less-or-equal) + `goto` in bytecode. High-level constructs flatten into jump instructions.

---

### 💻 Advanced — `invokedynamic` (Lambda bytecode)

This is where it gets deep. Java lambdas don't compile to anonymous classes (as many think) — they use `invokedynamic`:

java

```java
// Source
Runnable r = () -> System.out.println("hello");
```

bash

```bash
javap -c -p LambdaDemo
```

```
// Bytecode
invokedynamic #2, 0   // Bootstrap method decides AT RUNTIME
                      // how to create the lambda implementation
```

> `invokedynamic` is the foundation of lambdas, method references, and string concatenation (Java 9+). It defers method dispatch to **runtime** rather than compile time — making the JVM extensible without changing the language.

---

### 🔁 Bytecode in the Full Execution Flow

```
.java source
     ↓ javac
.class (bytecode)
     ↓ ClassLoader reads into JVM
Bytecode in memory
     ↓
┌────────────────────────────────────────┐
│        EXECUTION ENGINE                │
│                                        │
│  Interpreter                           │
│  (executes bytecode directly)          │
│  Fast startup, slow sustained          │
│         ↓                              │
│  Profiler detects HOT methods          │
│  (called > threshold, e.g. 10,000x)   │
│         ↓                              │
│  JIT Compiler (C1 → C2)               │
│  Bytecode → Native Machine Code        │
│  Cached — never interpreted again      │
└────────────────────────────────────────┘
     ↓
Native code runs at CPU speed
```

---

### ⚙️ Major Version Numbers — Java Version Detection

java

```java
// Every .class file has a major version number
// JVM checks this on load — rejects if too new

Major Version → Java Version
45  → Java 1.1
52  → Java 8
55  → Java 11
61  → Java 17
65  → Java 21
```

bash

```bash
# Check a .class file's Java version (raw hex)
xxd Calculator.class | head -1
# Output: cafe babe 0000 0041
#                        ^^^^ = 0x41 = 65 decimal = Java 21

# Or just use javap:
javap -verbose Calculator.class | grep "major version"
# major version: 65
```

This is why you get `UnsupportedClassVersionError` — your JRE is older than the bytecode's major version.

---

### ⚠️ Common Misconceptions

|Misconception|Reality|
|---|---|
|"Bytecode is machine code"|No — it's an intermediate format for JVM, not CPU|
|"Bytecode is Java-only"|Kotlin, Scala, Groovy all compile to the same JVM bytecode|
|"Bytecode can't be reversed"|Tools like CFR, Procyon, Fernflower decompile bytecode back to readable Java|
|"Lambdas compile to anonymous classes"|They use `invokedynamic` — much more efficient|
|"Bytecode is slow vs native"|JIT-compiled hot bytecode reaches near-native performance|

---

### 🔥 Pitfalls in Production

**1. Bytecode manipulation libraries — know what you're injecting**

java

```java
// Frameworks like Spring, Hibernate, ByteBuddy, ASM
// modify bytecode at runtime (CGLIB proxies, JPA lazy loading)

// If you see weird behavior in proxied classes:
// - toString() not called on real object
// - equals() failing on same object
// → You're likely looking at a proxy, not the real class

// Debug: check class name at runtime
System.out.println(myBean.getClass().getName());
// Output: com.example.Service$$EnhancerBySpringCGLIB$$1a2b3c
//                           ^^^ this is bytecode-generated proxy
```

**2. Obfuscation vs decompilation risk**

bash

```bash
# Your shipped .jar bytecode CAN be decompiled
# Use ProGuard or R8 to obfuscate if shipping to clients

# Without obfuscation:
# CFR decompiler can recover ~95% of original source
java -jar cfr.jar myapp.jar --outputdir decompiled/
```

**3. Version targeting for compatibility**

bash

```bash
# Compile for older JVM compatibility
javac --release 11 MyApp.java
# Produces major version 55, runs on Java 11+

# Without --release: compiles for current JDK version
# Deployed to Java 11 server → UnsupportedClassVersionError
```

---

### 🔗 Related Keywords

- `JVM` — executes bytecode
- `javac` — produces bytecode from source
- `javap` — disassembles bytecode for inspection
- `Class Loader` — loads bytecode into JVM memory
- `JIT Compiler` — compiles hot bytecode → native code
- `Interpreter` — executes bytecode directly (before JIT)
- `invokedynamic` — runtime-resolved method dispatch (lambdas)
- `ASM / ByteBuddy` — libraries that generate/modify bytecode
- `Stack Frame` — execution context per method (where bytecode runs)
- `Operand Stack` — the stack bytecode instructions operate on

---

### 📌 Quick Reference Card

---

### 🧠 Think About This Before We Continue

Two sharp questions to build your instinct:

**Q1.** Kotlin compiles to the same JVM bytecode as Java. What does that mean for interoperability — and what are its limits?

**Q2.** If JIT-compiled bytecode reaches near-native speed, why would anyone use GraalVM Native Image (which compiles ahead-of-time)? What problem does it solve that JIT can't?
